learn_rec_algorithm
