Metadata-Version: 2.1
Name: learn-rec-algorithm
Version: 0.0.7
Summary: Private project for learning recommendation algorithm
Home-page: https://github.com/lukun2010/learn_rec_algorithm
Author: lukun2010
Author-email: lukun@live.cn
License: MIT License
Keywords: recommendation,algorithm
Platform: any
License-File: LICENSE
